keys2text_proxy/__init__.py
keys2text_proxy/api_anthropic.py
keys2text_proxy/api_deepseek.py
keys2text_proxy/api_google.py
keys2text_proxy/api_google_openai.py
keys2text_proxy/api_groq.py
keys2text_proxy/api_lmstudio.py
keys2text_proxy/api_mock.py
keys2text_proxy/api_ollama.py
keys2text_proxy/api_openai.py
keys2text_proxy/api_openrouter.py
keys2text_proxy/main.py
keys2text_proxy-2025.1.1.10.dist-info/LICENSE
keys2text_proxy-2025.1.1.10.dist-info/METADATA
keys2text_proxy-2025.1.1.10.dist-info/WHEEL
keys2text_proxy-2025.1.1.10.dist-info/entry_points.txt
keys2text_proxy-2025.1.1.10.dist-info/top_level.txt
keys2text_proxy-2025.1.1.10.dist-info/RECORD
